FaceGuard/__init__.py
FaceGuard/faces.py
FaceGuard/recognition.py
FaceGuard/utils.py
FaceGuard-0.1.dist-info/METADATA
FaceGuard-0.1.dist-info/WHEEL
FaceGuard-0.1.dist-info/top_level.txt
FaceGuard-0.1.dist-info/RECORD
